sopel_anilist/__init__.py
sopel_anilist-0.2.0.dist-info/COPYING
sopel_anilist-0.2.0.dist-info/METADATA
sopel_anilist-0.2.0.dist-info/WHEEL
sopel_anilist-0.2.0.dist-info/entry_points.txt
sopel_anilist-0.2.0.dist-info/top_level.txt
sopel_anilist-0.2.0.dist-info/RECORD
