Metadata-Version: 2.1
Name: sopel-anilist
Version: 0.2.0
Summary: AniList plugin for Sopel IRC bots
Author-email: dgw <dgw@technobabbl.es>
License: EFL-2.0
Project-URL: Homepage, https://github.com/dgw/sopel-anilist
Project-URL: Bug Tracker, https://github.com/dgw/sopel-anilist/issues
Keywords: sopel,plugin,bot,irc
Platform: Linux x86, x86-64
Classifier: Intended Audience :: Developers
Classifier: Intended Audience :: System Administrators
Classifier: License :: Eiffel Forum License (EFL)
Classifier: License :: OSI Approved :: Eiffel Forum License
Classifier: Programming Language :: Python :: 3 :: Only
Classifier: Topic :: Communications :: Chat :: Internet Relay Chat
Requires-Python: <4,>=3.8
License-File: COPYING
Requires-Dist: sopel>=7.1
Requires-Dist: requests
Requires-Dist: bleach>=6.0
